README.md
requirements.txt
setup.py
ebs_snapper/__init__.py
ebs_snapper/clean.py
ebs_snapper/deploy.py
ebs_snapper/dynamo.py
ebs_snapper/lambdas.py
ebs_snapper/mocks.py
ebs_snapper/replication.py
ebs_snapper/shell.py
ebs_snapper/snapshot.py
ebs_snapper/utils.py
ebs_snapper.egg-info/PKG-INFO
ebs_snapper.egg-info/SOURCES.txt
ebs_snapper.egg-info/dependency_links.txt
ebs_snapper.egg-info/entry_points.txt
ebs_snapper.egg-info/requires.txt
ebs_snapper.egg-info/top_level.txt