Metadata-Version: 1.0
Name: ebs-snapper
Version: 0.10.2
Summary: Collection of AWS Lambda functions create, manage, and delete EBS snapshots
Home-page: https://github.com/rackerlabs/ebs_snapper
Author: Rackspace
Author-email: fps@rackspace.com
License: UNKNOWN
Keywords: aws lambda ebs ec2 snapshot backup
Platform: UNKNOWN
